pard/__init__.py
pard/_handling_3_letter_code_decorator.py
pard/_raw_python_dictionaries.py
pard/empar.py
pard/epstein.py
pard/experimental_exchangeability.py
pard/grantham.py
pard/kolaskar.py
pard/koshi_goldstein.py
pard/miyata.py
pard/pairwise_distance.py
pard/sneath.py
pard-0.7.0.1.dist-info/WHEEL
pard-0.7.0.1.dist-info/METADATA
pard-0.7.0.1.dist-info/RECORD
