Metadata-Version: 2.1
Name: pard
Version: 0.7.0.1
Summary: Physicochemical Amino acid Replacement Distances
Author: JasonMendoza2008
Author-email: lhotteromain@gmail.com
Requires-Python: >=3.10,<4.0
Classifier: Programming Language :: Python :: 3
Classifier: Programming Language :: Python :: 3.10
Classifier: Programming Language :: Python :: 3.11
